syncster_ioc/_version.py
syncster_ioc/application.py
syncster_ioc/delay_dds.py
syncster_ioc/ioc.py
syncster_ioc/main.py
syncster_ioc/sync_mock.py
syncster_ioc/sync_rre.py
syncster_ioc/syncro_engine.py
syncster_ioc/syncro_ioc.py
syncster_ioc-0.1.2.dist-info/METADATA
syncster_ioc-0.1.2.dist-info/WHEEL
syncster_ioc-0.1.2.dist-info/entry_points.txt
syncster_ioc-0.1.2.dist-info/top_level.txt
syncster_ioc-0.1.2.dist-info/RECORD
