Metadata-Version: 2.1
Name: syncster-ioc
Version: 0.1.2
Summary: EPICS IOC for syncronisation applications in Pump-Probe X-ray diffraction
Author-email: Florin Boariu <florin.pt@rootshell.ro>, Matthias Rössle <matthias.roessle@helmholtz-berlin.de>
Project-URL: Source Code, https://gitlab.com/kmc3-xpp/syncster-ioc
Classifier: Programming Language :: Python :: 3
Classifier: License :: OSI Approved :: GNU General Public License v3 or later (GPLv3+)
Classifier: Operating System :: POSIX :: Linux
Classifier: Development Status :: 2 - Pre-Alpha
Classifier: Environment :: Console
Classifier: Intended Audience :: Science/Research
Classifier: Topic :: Scientific/Engineering
Requires-Python: >=3.8
Requires-Dist: emmi >=0.6.0
Requires-Dist: caproto
Requires-Dist: menlo-syncro
Provides-Extra: test
Requires-Dist: pytest ; extra == 'test'
Requires-Dist: pytest-cov ; extra == 'test'
Requires-Dist: pytest-asyncio ; extra == 'test'
